aipkgs_core/__init__.py
aipkgs_core/decorators/helpers.py
aipkgs_core/encryption/encryption.py
aipkgs_core/jwt/helpers.py
aipkgs_core/jwt/model.py
aipkgs_core/logger/helpers.py
aipkgs_core/responses/error.py
aipkgs_core/responses/response.py
aipkgs_core/responses/success.py
aipkgs_core/responses/verbose.py
aipkgs_core/utils/date_helpers.py
aipkgs_core/utils/dir_helpers.py
aipkgs_core/utils/email.py
aipkgs_core/utils/file_helpers.py
aipkgs_core/utils/json.py
aipkgs_core/utils/phone.py
aipkgs_core/utils/singleton.py
aipkgs_core/utils/string_helpers.py
aipkgs_core/utils/utils.py
aipkgs_core-1.0.19.dist-info/LICENSE.md
aipkgs_core-1.0.19.dist-info/METADATA
aipkgs_core-1.0.19.dist-info/WHEEL
aipkgs_core-1.0.19.dist-info/RECORD
