Metadata-Version: 2.1
Name: aipkgs-core
Version: 1.0.19
Summary: Core package for aipy packages.
Home-page: https://gitlab.com/aipy/public/packages.git
License: MIT
Keywords: ai
Author: Alexy
Author-email: alexy.ib@outlook.com
Requires-Python: >=3.11.4,<4.0.0
Classifier: License :: OSI Approved :: MIT License
Classifier: Programming Language :: Python :: 3
Classifier: Programming Language :: Python :: 3.12
Requires-Dist: aipkgs-requests (>=1.0.0,<2.0.0)
Requires-Dist: bcrypt (>=4.1.3,<5.0.0)
Requires-Dist: email-validator (>=2.1.1,<3.0.0)
Requires-Dist: emoji (>=2.11.1,<3.0.0)
Requires-Dist: flask-jwt-extended (>=4.6.0,<5.0.0)
Requires-Dist: pendulum (>=2.0.0,<3.0.0)
Requires-Dist: phonenumbers (>=8.13.36,<9.0.0)
Requires-Dist: requests (>=2.28.1,<3.0.0)
Project-URL: Repository, https://gitlab.com/aipy/public/packages.git
